datasette_create_view/__init__.py
datasette_create_view/templates/create_view.html
datasette_create_view-0.1.dist-info/LICENSE
datasette_create_view-0.1.dist-info/METADATA
datasette_create_view-0.1.dist-info/WHEEL
datasette_create_view-0.1.dist-info/entry_points.txt
datasette_create_view-0.1.dist-info/top_level.txt
datasette_create_view-0.1.dist-info/RECORD
