Metadata-Version: 2.1
Name: datasette-create-view
Version: 0.1
Summary: Create a SQL view from a query
Author: Simon Willison
License: Apache-2.0
Project-URL: Homepage, https://github.com/datasette/datasette-create-view
Project-URL: Changelog, https://github.com/datasette/datasette-create-view/releases
Project-URL: Issues, https://github.com/datasette/datasette-create-view/issues
Project-URL: CI, https://github.com/datasette/datasette-create-view/actions
Classifier: Framework :: Datasette
Classifier: License :: OSI Approved :: Apache Software License
Requires-Python: >=3.8
License-File: LICENSE
Requires-Dist: datasette >=1.0a12
Provides-Extra: test
Requires-Dist: pytest ; extra == 'test'
Requires-Dist: pytest-asyncio ; extra == 'test'
